pineflow/readers/docling/__init__.py
pineflow/readers/docling/base.py
pineflow_readers_docling-0.7.3.dist-info/METADATA
pineflow_readers_docling-0.7.3.dist-info/WHEEL
pineflow_readers_docling-0.7.3.dist-info/RECORD
