Metadata-Version: 2.4
Name: pineflow-readers-docling
Version: 0.7.3
Summary: pineflow readers docling extension
Author-email: Leonardo Furnielis <leonardofurnielis@outlook.com>
License: MIT
Requires-Python: <4.0,>=3.10
Requires-Dist: docling<3.0.0,>=2.37.0
Requires-Dist: pineflow-core<0.8.0,>=0.7.2
Requires-Dist: torch==2.2.2
Provides-Extra: dev
Requires-Dist: ruff>=0.11.13; extra == 'dev'
